PSIPREDauto/__init__.py
PSIPREDauto/commandline.py
PSIPREDauto/functions.py
PSIPREDauto-0.0.1.1.1.dist-info/LICENSE
PSIPREDauto-0.0.1.1.1.dist-info/METADATA
PSIPREDauto-0.0.1.1.1.dist-info/WHEEL
PSIPREDauto-0.0.1.1.1.dist-info/top_level.txt
PSIPREDauto-0.0.1.1.1.dist-info/RECORD
