Metadata-Version: 2.1
Name: PSIPREDauto
Version: 0.0.1.1.1
Summary: Automated submission to the PSIPRED protein secondary structure calculator REST API.
Author: Piers Wilkinson
Author-email: pnw2@hotmail.co.uk
License: UNKNOWN
Platform: UNKNOWN
Classifier: Programming Language :: Python :: 3
Classifier: License :: OSI Approved :: MIT License
Classifier: Operating System :: OS Independent
Requires-Python: >=3.6
License-File: LICENSE
